resourcemaxxing/__init__.py
resourcemaxxing/main.py
resourcemaxxing/maximalizer.py
resourcemaxxing/stdlog.py
resourcemaxxing/teal.py
resourcemaxxing/tests/__init__.py
resourcemaxxing/tests/cpu.py
resourcemaxxing/tests/gpu.py
resourcemaxxing/tests/net.py
resourcemaxxing/tests/ram.py
resourcemaxxing-0.1.2.dist-info/LICENSE
resourcemaxxing-0.1.2.dist-info/METADATA
resourcemaxxing-0.1.2.dist-info/WHEEL
resourcemaxxing-0.1.2.dist-info/entry_points.txt
resourcemaxxing-0.1.2.dist-info/top_level.txt
resourcemaxxing-0.1.2.dist-info/RECORD
