Metadata-Version: 2.2
Name: resourcemaxxing
Version: 0.1.2
Summary: Resources not being used are resources wasted.
Author-email: Issac Liu <issac@matchatea.dev>, Jan Koch <meepstertron@gmail.com>
License: MIT
Requires-Python: >=3.13
License-File: LICENSE
Requires-Dist: aiohttp>=3.11.13
Requires-Dist: colored>=2.3.0
Requires-Dist: gputil>=1.4.0
Requires-Dist: numpy>=2.2.3
Requires-Dist: psutil>=7.0.0
Requires-Dist: tk>=0.1.0
Requires-Dist: torch>=2.6.0
Requires-Dist: twine>=6.1.0
